timespan/__init__.py
timespan/timespan.py
timespan_python-0.1.2.dist-info/METADATA
timespan_python-0.1.2.dist-info/WHEEL
timespan_python-0.1.2.dist-info/top_level.txt
timespan_python-0.1.2.dist-info/RECORD
